{
  "video_id": "3x4h25rqxf99t7i",
  "stats": {
    "video_name": "3x4h25rqxf99t7i.mp4",
    "num_shots": 3,
    "avg_shot_len_sec": 2.111,
    "cuts_per_30s": 9.375,
    "editing_rhythm_guess": "very_fast",
    "lighting": {
      "quality": "medium_contrast",
      "condition": "overcast_neutral",
      "color_temperature": "cool_tone",
      "s_mean": 0.203,
      "v_mean": 0.516,
      "v_std": 0.217
    },
    "movement_counts": {
      "static_shot": 1,
      "pan_horizontal": 1,
      "tilt_vertical": 1,
      "dolly_in": 0,
      "dolly_out": 0
    }
  },
  "analysis": {
    "video_analysis": {
      "shot_types": [
        "medium_shot"
      ],
      "camera_movements": [
        "static_shot"
      ],
      "editing_rhythm": "very_fast",
      "composition_styles": [
        "rule_of_thirds"
      ],
      "color_tone": "cool_tone",
      "lighting_style": "medium_contrast",
      "overall_style": [
        "documentary_style",
        "narrative_style"
      ],
      "confidence_score": 0.3
    },
    "style_tags": [
      "narrative_style",
      "static_shot",
      "cool_tone",
      "rule_of_thirds",
      "medium_shot",
      "documentary_style",
      "medium_contrast",
      "very_fast"
    ]
  }
}