{
  "video_id": "3x7f6bxg4j46cdk",
  "stats": {
    "video_name": "3x7f6bxg4j46cdk.mp4",
    "num_shots": 2,
    "avg_shot_len_sec": 3.717,
    "cuts_per_30s": 4.018,
    "editing_rhythm_guess": "moderate",
    "lighting": {
      "quality": "medium_contrast",
      "condition": "overcast_neutral",
      "color_temperature": "cool_tone",
      "s_mean": 0.207,
      "v_mean": 0.558,
      "v_std": 0.21
    },
    "movement_counts": {
      "static_shot": 2,
      "pan_horizontal": 0,
      "tilt_vertical": 0,
      "dolly_in": 0,
      "dolly_out": 0
    }
  },
  "analysis": {
    "video_analysis": {
      "shot_types": [
        "medium_shot"
      ],
      "camera_movements": [
        "static_shot"
      ],
      "editing_rhythm": "moderate",
      "composition_styles": [
        "rule_of_thirds"
      ],
      "color_tone": "cool_tone",
      "lighting_style": "medium_contrast",
      "overall_style": [
        "documentary_style",
        "narrative_style"
      ],
      "confidence_score": 0.3
    },
    "style_tags": [
      "narrative_style",
      "static_shot",
      "cool_tone",
      "rule_of_thirds",
      "medium_shot",
      "documentary_style",
      "medium_contrast",
      "moderate"
    ]
  }
}